pwcp/__init__.py
pwcp/__main__.py
pwcp/config.py
pwcp/errors.py
pwcp/hooks.py
pwcp/monkeypatch.py
pwcp/preprocessor.py
pwcp/runner.py
pwcp/utils.py
pwcp/version.py
pwcp-0.12.1.dist-info/METADATA
pwcp-0.12.1.dist-info/WHEEL
pwcp-0.12.1.dist-info/entry_points.txt
pwcp-0.12.1.dist-info/licenses/LICENSE.md
pwcp-0.12.1.dist-info/RECORD
