Metadata-Version: 2.4
Name: pwcp
Version: 0.12.1
Summary: Python with C preprocessor
Project-URL: Repository, https://github.com/solaluset/pwcp
License-Expression: MIT
License-File: LICENSE.md
Requires-Python: >=3.7
Requires-Dist: pypp-for-pwcp==1.33b5
Provides-Extra: tests
Requires-Dist: pytest; extra == 'tests'
